LICENSE
README.md
setup.py
nl_causal/__init__.py
nl_causal/base/__init__.py
nl_causal/base/preprocessing.py
nl_causal/base/rv.py
nl_causal/base/sim_data.py
nl_causal/base/testing.py
nl_causal/sparse_reg/__init__.py
nl_causal/sparse_reg/sparse_reg.py
nl_causal/ts_models/__init__.py
nl_causal/ts_models/_base.py
nl_causal/ts_models/ts_twas.py
nonlinear_causal.egg-info/PKG-INFO
nonlinear_causal.egg-info/SOURCES.txt
nonlinear_causal.egg-info/dependency_links.txt
nonlinear_causal.egg-info/requires.txt
nonlinear_causal.egg-info/top_level.txt