Metadata-Version: 2.1
Name: nonlinear-causal
Version: 1.0
Summary: nonlinear-causal is a Python module for nonlinear causal inference built on top of Two-stage IV methods.
Home-page: https://github.com/statmlben/nonlinear-causal
Author: Ben Dai
Author-email: bendai@cuhk.edu.hk
License: MIT
License-File: LICENSE
Requires-Dist: numpy
Requires-Dist: pandas
Requires-Dist: sliced
Requires-Dist: scipy
Requires-Dist: scikit-learn
Requires-Dist: statsmodels
